jupyterlab_ui_profiler/__init__.py
jupyterlab_ui_profiler/_version.py
jupyterlab_ui_profiler-0.3.0.data/data/etc/jupyter/jupyter_notebook_config.d/jupyterlab_ui_profiler.json
jupyterlab_ui_profiler-0.3.0.data/data/etc/jupyter/jupyter_server_config.d/jupyterlab_ui_profiler.json
jupyterlab_ui_profiler-0.3.0.data/data/share/jupyter/labextensions/@jupyterlab/ui-profiler/package.json
jupyterlab_ui_profiler-0.3.0.data/data/share/jupyter/labextensions/@jupyterlab/ui-profiler/static/166.694a1f53bf9fdbf4f180.js
jupyterlab_ui_profiler-0.3.0.data/data/share/jupyter/labextensions/@jupyterlab/ui-profiler/static/196.a96a9d25fee1bdb59cb1.js
jupyterlab_ui_profiler-0.3.0.data/data/share/jupyter/labextensions/@jupyterlab/ui-profiler/static/196.a96a9d25fee1bdb59cb1.js.LICENSE.txt
jupyterlab_ui_profiler-0.3.0.data/data/share/jupyter/labextensions/@jupyterlab/ui-profiler/static/728.dcbbede0248e754c49eb.js
jupyterlab_ui_profiler-0.3.0.data/data/share/jupyter/labextensions/@jupyterlab/ui-profiler/static/remoteEntry.bd91069026781369b87a.js
jupyterlab_ui_profiler-0.3.0.data/data/share/jupyter/labextensions/@jupyterlab/ui-profiler/static/style.js
jupyterlab_ui_profiler-0.3.0.data/data/share/jupyter/labextensions/@jupyterlab/ui-profiler/static/third-party-licenses.json
jupyterlab_ui_profiler-0.3.0.data/data/share/jupyter/labextensions/@jupyterlab/ui-profiler/install.json
jupyterlab_ui_profiler-0.3.0.dist-info/METADATA
jupyterlab_ui_profiler-0.3.0.dist-info/WHEEL
jupyterlab_ui_profiler-0.3.0.dist-info/licenses/LICENSE
jupyterlab_ui_profiler-0.3.0.dist-info/RECORD
